liquid_engine/__agent__.py
liquid_engine/__cuda__.py
liquid_engine/__dask__.py
liquid_engine/__init__.py
liquid_engine/__njit__.py
liquid_engine/__opencl__.py
liquid_engine/__transonic__.py
liquid_engine/liquid_engine.py
liquid_engine-0.1.11.dist-info/METADATA
liquid_engine-0.1.11.dist-info/WHEEL
liquid_engine-0.1.11.dist-info/top_level.txt
liquid_engine-0.1.11.dist-info/RECORD
