Metadata-Version: 2.4
Name: liquid_engine
Version: 0.1.11
Summary: Liquid Engine standalone Python package
Author: Bruno M. Saraiva, António D. Brito, Inês M. Cunha, Ricardo Henriques
Author-email: bruno.msaraiva2@gmail.com, antmsbrito95@gmail.com, inescunha200@gmail.com, ricardo.jv.henriques@gmail.com
Classifier: Operating System :: OS Independent
Classifier: Programming Language :: Python
Classifier: Programming Language :: Python :: 3
Classifier: Topic :: Software Development :: Testing
Requires-Python: >=3.9
Requires-Dist: numpy<2,>=1.22
Requires-Dist: scikit-learn>=1.1.0
Requires-Dist: scipy>=1.8
Requires-Dist: pyyaml>=6.0
Requires-Dist: importlib_resources
